building_energy_standards_data/__init__.py
building_energy_standards_data/applications/__init__.py
building_energy_standards_data/applications/create_openstudio_standards_json.py
building_energy_standards_data/applications/database_maintenance.py
building_energy_standards_data/applications/form/__init__.py
building_energy_standards_data/applications/form/update_space_data.py
building_energy_standards_data/client.py
building_energy_standards_data/database_engine/__init__.py
building_energy_standards_data/database_engine/assertions.py
building_energy_standards_data/database_engine/database.py
building_energy_standards_data/database_engine/database_util.py
building_energy_standards_data/database_files/envelope_requirements_90_1.json
building_energy_standards_data/database_files/envelope_requirements_90_1_prm.json
building_energy_standards_data/database_files/envelope_requirements_IECC.json
building_energy_standards_data/database_files/envelope_thermal_bridging_requirements_90_1.json
building_energy_standards_data/database_files/envelope_thermal_bridging_requirements_IECC.json
building_energy_standards_data/database_files/exterior_lighting_90_1.json
building_energy_standards_data/database_files/exterior_lighting_90_1_prm.json
building_energy_standards_data/database_files/exterior_lighting_IECC.json
building_energy_standards_data/database_files/hvac_minimum_requirements_boilers_189_1.json
building_energy_standards_data/database_files/hvac_minimum_requirements_boilers_90_1.json
building_energy_standards_data/database_files/hvac_minimum_requirements_boilers_90_1_prm.json
building_energy_standards_data/database_files/hvac_minimum_requirements_boilers_IECC.json
building_energy_standards_data/database_files/hvac_minimum_requirements_chillers_189_1.json
building_energy_standards_data/database_files/hvac_minimum_requirements_chillers_90_1.json
building_energy_standards_data/database_files/hvac_minimum_requirements_chillers_90_1_prm.json
building_energy_standards_data-0.2.1.dist-info/LICENSE.md
building_energy_standards_data-0.2.1.dist-info/METADATA
building_energy_standards_data-0.2.1.dist-info/WHEEL
building_energy_standards_data-0.2.1.dist-info/RECORD
