Metadata-Version: 2.3
Name: building-energy-standards-data
Version: 0.2.1
Summary: 
Author: Lerond, Jeremy
Author-email: jeremy.lerond@pnnl.gov
Requires-Python: >=3.10,<4.0
Classifier: Programming Language :: Python :: 3
Classifier: Programming Language :: Python :: 3.10
Classifier: Programming Language :: Python :: 3.11
Classifier: Programming Language :: Python :: 3.12
Classifier: Programming Language :: Python :: 3.13
Requires-Dist: black (==22.12.0)
Requires-Dist: pytest (>=7.4.3,<8.0.0)
